pixel_map-0.2.4.dist-info/METADATA
pixel_map-0.2.4.dist-info/WHEEL
pixel_map-0.2.4.dist-info/entry_points.txt
pixel_map-0.2.4.dist-info/licenses/LICENSE
pixel_map/__init__.py
pixel_map/__main__.py
pixel_map/example_files/london_buildings.parquet
pixel_map/example_files/london_park.parquet
pixel_map/example_files/london_water.parquet
pixel_map/example_files/monaco_buildings.parquet
pixel_map/plotter.py
pixel_map/renderers.py
pixel_map-0.2.4.dist-info/RECORD
