Metadata-Version: 2.1
Name: pixel-map
Version: 0.2.4
Summary: A Python CLI tool for plotting geo files in the terminal
Author-Email: Kamil Raczycki <kraczycki@kraina.ai>
License: MIT
Classifier: Development Status :: 3 - Alpha
Classifier: License :: OSI Approved :: MIT License
Classifier: Topic :: Scientific/Engineering :: GIS
Classifier: Intended Audience :: Science/Research
Classifier: Intended Audience :: Developers
Classifier: Programming Language :: Python :: 3
Classifier: Programming Language :: Python :: 3.9
Classifier: Programming Language :: Python :: 3.10
Classifier: Programming Language :: Python :: 3.11
Classifier: Programming Language :: Python :: 3.12
Classifier: Operating System :: Unix
Classifier: Operating System :: MacOS
Classifier: Operating System :: Microsoft :: Windows
Project-URL: Homepage, https://github.com/RaczeQ/pixel-map
Project-URL: Repository, https://github.com/RaczeQ/pixel-map
Project-URL: Changelog, https://github.com/RaczeQ/pixel-map/blob/main/CHANGELOG.md
Requires-Python: >=3.9
Requires-Dist: rich>=12.0.0
Requires-Dist: typer[all]>=0.9.0
Requires-Dist: img2unicode[n2]>=0.1a11; sys_platform != "win32" and sys_platform != "darwin"
Requires-Dist: img2unicode>=0.1a11; sys_platform == "win32" or sys_platform == "darwin"
Requires-Dist: geopandas>=0.8
Requires-Dist: numpy>=1.26.0
Requires-Dist: contextily>=1
Requires-Dist: matplotlib>=3.2.0
Requires-Dist: pyarrow>=16.0.0
